{
  "product": "e - Housing Solutions Licence",
  "channel": "stable",
  "latestVersion": "v175",
  "releasedAt": "2026-07-12",
  "minimumSupportedVersion": "v170",
  "summary": "Verzia v175 pridáva oddelenú Partnerskú zónu pre Platform Admina, sprievodcu novou inštaláciou a auditovaný servisný prístup k samostatným partnerským inštaláciám.",
  "changes": [
    "Platform Admin má samostatnú Partnerskú zónu so zoznamom inštalácií, vyhľadávaním, stavmi a detailom služieb.",
    "Nová inštalácia používa kontrolovaný postup pre samostatný GitHub, Supabase, Vercel a Gmail účet konkrétneho domu.",
    "Servisný vstup používa krátkodobý podpísaný odkaz, povinný dôvod vstupu a auditný log.",
    "Čistý inštalačný balík automaticky vypína centrálnu Partnerskú zónu a neobsahuje jej vydávaciu funkciu."
  ],
  "updateMode": "manifest_check_manual_deploy",
  "releaseUrl": "https://github.com/SVBDruzstevna386/e-housing",
  "updateRequestUrl": "",
  "sourceRepository": "private",
  "notes": "Aktualizáciu produkčnej inštalácie musí potvrdiť oprávnený správca a vykonať bezpečný deploy proces."
}
