{
  "product": "e - Housing Solutions Licence",
  "channel": "stable",
  "latestVersion": "v189",
  "releasedAt": "2026-07-24",
  "minimumSupportedVersion": "v170",
  "summary": "Verzia v189 upravuje názvy položiek hlavného menu.",
  "changes": [
    "Položka Nahlás poruchu bola premenovaná na Nahlásiť poruchu.",
    "Položka Denník bola premenovaná na Denník SVB.",
    "PWA cache bola zvýšená na v189."
  ],
  "updateMode": "manifest_check_manual_deploy",
  "releaseUrl": "https://github.com/SVBDruzstevna386/e-housing",
  "updateRequestUrl": "",
  "sourceRepository": "private",
  "notes": "Na serverovej strane musí byť nastavený Supabase secret GITHUB_BOOTSTRAP_TOKEN s právom zápisu do cieľového GitHub repozitára."
}
